coze_workflow.py
mseep_coze_workflow_mcp-0.1.2.dist-info/METADATA
mseep_coze_workflow_mcp-0.1.2.dist-info/WHEEL
mseep_coze_workflow_mcp-0.1.2.dist-info/top_level.txt
mseep_coze_workflow_mcp-0.1.2.dist-info/RECORD
